aci_mcp/.env
aci_mcp/Dockerfile
aci_mcp/__init__.py
aci_mcp/main.py
aci_mcp/main_test.py
aci_mcp/requirements.txt
aci_mcp/urls.json
iflow_mcp_automateyournetwork_aci_mcp-0.1.4.data/data/aci_mcp/urls.json
iflow_mcp_automateyournetwork_aci_mcp-0.1.4.dist-info/METADATA
iflow_mcp_automateyournetwork_aci_mcp-0.1.4.dist-info/WHEEL
iflow_mcp_automateyournetwork_aci_mcp-0.1.4.dist-info/entry_points.txt
iflow_mcp_automateyournetwork_aci_mcp-0.1.4.dist-info/licenses/LICENSE
iflow_mcp_automateyournetwork_aci_mcp-0.1.4.dist-info/RECORD
