Metadata-Version: 2.4
Name: iflow-mcp-automateyournetwork-aci-mcp
Version: 0.1.4
Summary: A Model Context Protocol (MCP) server that provides full CRUD access to the Cisco ACI API
License-File: LICENSE
Requires-Python: >=3.8
Requires-Dist: fastmcp<2.0
Requires-Dist: pydantic>=2.0.0
Requires-Dist: python-dotenv>=1.0.0
Requires-Dist: requests>=2.31.0
